peppol_py/__init__.py
peppol_py/__main__.py
peppol_py/as4.py
peppol_py/as4_sender.py
peppol_py/constants.py
peppol_py/exception.py
peppol_py/sender.py
peppol_py/smp.py
peppol_py/statistics.py
peppol_py/validation.py
peppol_py/wsse.py
peppol_py/xmlhelpers.py
peppol_py/data/certs/README.md
peppol_py/data/certs/ap-prod-truststore-g2-g3.p12
peppol_py/data/certs/ap-prod-truststore-g2-g3.pem
peppol_py/data/certs/ap-prod-truststore-g3.pem
peppol_py/data/certs/ap-test-truststore-g2-g3.p12
peppol_py/data/certs/ap-test-truststore-g2-g3.pem
peppol_py/data/certs/ap-test-truststore-g3.pem
peppol_py/data/sendpeppol-schematron/CEN-EN16931-UBL.xsl
peppol_py/data/sendpeppol-schematron/PEPPOL-EN16931-UBL.xsl
peppol_py/data/sendpeppol-schematron/peppol-end-user-statistics-reporting-1.1.4.xsl
peppol_py/data/sendpeppol-schematron/peppol-transaction-statistics-reporting-1.0.4.xsl
peppol_py/data/xmlsec/README.md
peppol_py/data/xmlsec/sendpeppol_encrypt_template.xml
peppol_py/data/xsd/README.md
peppol_py/data/xsd/ebms-header-3_0-200704.xsd
peppol_py/data/xsd/multiple.xsd
peppol_py/data/xsd/soap-envelope.xsd
peppol_py-1.1.2.dist-info/licenses/LICENSE
peppol_py-1.1.2.dist-info/METADATA
peppol_py-1.1.2.dist-info/WHEEL
peppol_py-1.1.2.dist-info/top_level.txt
peppol_py-1.1.2.dist-info/RECORD
