Metadata-Version: 2.4
Name: peppol-py
Version: 1.1.2
Summary: A python implementation for sending peppol eDelivery AS4 documents.
Author: Anders Rune Jensen, Raphael Michel
License-Expression: 0BSD
Project-URL: Homepage, https://github.com/iterasdev/peppol-py
Project-URL: Issues, https://github.com/iterasdev/peppol-py/issues
Classifier: Programming Language :: Python :: 3
Classifier: Operating System :: OS Independent
Requires-Python: >=3.9
License-File: LICENSE
Requires-Dist: requests
Requires-Dist: lxml
Requires-Dist: xmlsec
Requires-Dist: asn1crypto
Requires-Dist: certvalidator
Requires-Dist: saxonche
Requires-Dist: dnspython==2.*
Provides-Extra: dev
Requires-Dist: pytest; extra == "dev"
Dynamic: license-file
